DecoderLibrary/__init__.py
rf_decoderlibrary-0.1.1a1.dist-info/LICENSE
rf_decoderlibrary-0.1.1a1.dist-info/METADATA
rf_decoderlibrary-0.1.1a1.dist-info/WHEEL
rf_decoderlibrary-0.1.1a1.dist-info/top_level.txt
rf_decoderlibrary-0.1.1a1.dist-info/RECORD
