Metadata-Version: 2.1
Name: rf-decoderlibrary
Version: 0.1.1a1
Summary: Test Library for Decoding Encoded Data.
Home-page: https://github.com/MainSystemDev
Author: Joshua Kim Rivera
Author-email: joshua.rivera@mnltechnology.com
License: Type license() to see the full license text
Platform: any
Classifier: Development Status :: 2 - Pre-Alpha
Classifier: License :: OSI Approved :: MIT License
Classifier: Operating System :: OS Independent
Classifier: Programming Language :: Python :: 3
Classifier: Topic :: Software Development :: Testing
Classifier: Framework :: Robot Framework
Classifier: Framework :: Robot Framework :: Library
Requires-Dist: certifi (==2019.11.28)
Requires-Dist: chardet (==3.0.4)
Requires-Dist: idna (==2.8)
Requires-Dist: Pillow (==6.2.0)
Requires-Dist: pypng (==0.0.20)
Requires-Dist: PyQRCode (==1.2.1)
Requires-Dist: pyzbar (==0.1.8)
Requires-Dist: requests (==2.22.0)
Requires-Dist: robotframework (==3.1.2)
Requires-Dist: robotlibcore-temp (==1.0.2)
Requires-Dist: urllib3 (==1.25.7)
